README.md
setup.py
pyencrypt/__init__.py
pyencrypt/encrypt/AesEncrypt.py
pyencrypt/encrypt/Base64Encrypt.py
pyencrypt/encrypt/Des3Encrypt.py
pyencrypt/encrypt/DesEncrypt.py
pyencrypt/encrypt/Encrypt.py
pyencrypt/encrypt/Md5Encrypt.py
pyencrypt/encrypt/RsaEncrypt.py
pyencrypt/encrypt/Sha1Encrypt.py
pyencrypt/encrypt/Sha256Encrypt.py
pyencrypt/encrypt/Sha512Encrypt.py
pyencrypt/encrypt/__init__.py
pyencrypt/ids/IdsCreator.py
pyencrypt/ids/SnowFlakeCreator.py
pyencrypt/ids/UUIDCreator.py
pyencrypt/ids/__init__.py
pyencrypt_plus.egg-info/PKG-INFO
pyencrypt_plus.egg-info/SOURCES.txt
pyencrypt_plus.egg-info/dependency_links.txt
pyencrypt_plus.egg-info/requires.txt
pyencrypt_plus.egg-info/top_level.txt